nonebot_plugin_deltaforce_price_search/__init__.py
nonebot_plugin_deltaforce_price_search/bullet_search.py
nonebot_plugin_deltaforce_price_search/config.py
nonebot_plugin_deltaforce_price_search-1.0.3.dist-info/licenses/LICENSE
nonebot_plugin_deltaforce_price_search-1.0.3.dist-info/METADATA
nonebot_plugin_deltaforce_price_search-1.0.3.dist-info/WHEEL
nonebot_plugin_deltaforce_price_search-1.0.3.dist-info/entry_points.txt
nonebot_plugin_deltaforce_price_search-1.0.3.dist-info/top_level.txt
nonebot_plugin_deltaforce_price_search-1.0.3.dist-info/RECORD
